phylogenetic_indices/__init__.py
phylogenetic_indices/indices.py
phylogenetic_indices-1.0.0.dist-info/LICENSE
phylogenetic_indices-1.0.0.dist-info/METADATA
phylogenetic_indices-1.0.0.dist-info/WHEEL
phylogenetic_indices-1.0.0.dist-info/RECORD
